agent/__init__.py
agent/agent_type.py
communication/__init__.py
communication/client/__init__.py
communication/client/connection/__init__.py
communication/client/connection/connection.py
communication/client/connection/interface.py
communication/client/protocol/__init__.py
communication/client/protocol/interface.py
communication/client/protocol/protocol.py
communication/server/__init__.py
communication/server/protocol/__init__.py
communication/server/protocol/function_code.py
communication/server/protocol/interface.py
communication/server/protocol/protocol.py
configuration/__init__.py
configuration/config.py
configuration/logconfig.py
data/__init__.py
data/common/__init__.py
data/common/enum/__init__.py
example/DataExample.py
example/DemoStrategy.py
example/FutureAbritrate.py
example/__init__.py
exception/__init__.py
exception/exception.py
scripts/__init__.py
scripts/server/__init__.py
scripts/server/server.py
strategy/__init__.py
strategy/interface.py
strategy/request.py
strategy/stragety.py
strategy/bean/__init__.py
strategy/bean/bean.py
strategy/bean/databean.py
strategy/bean/datatype.py
strategy/bean/enum/__init__.py
strategy/client/__init__.py
strategy/client/client.py
strategy/client/interface.py
strategy_sdk_py2-1.0.5.dist-info/DESCRIPTION.rst
strategy_sdk_py2-1.0.5.dist-info/METADATA
strategy_sdk_py2-1.0.5.dist-info/RECORD
strategy_sdk_py2-1.0.5.dist-info/WHEEL
strategy_sdk_py2-1.0.5.dist-info/metadata.json
strategy_sdk_py2-1.0.5.dist-info/top_level.txt
strategy_sdk_py2-1.0.5.dist-info/zip-safe
utils/__init__.py
utils/bean.py
utils/enum.py
utils/typing.py
utils/io/__init__.py
utils/io/io.py
