Metadata-Version: 2.0
Name: strategy-sdk-py2
Version: 1.0.5
Summary: this is a python2 client sdk for strategy access
Home-page: https://pypi.python.org/pypi/strategy-sdk-py2
Author: vector tang
Author-email: tangtao@hotmail.com
License: MIT
Keywords: p,y,t,h,o,n,2, ,s,t,r,a,t,e,g,y, ,s,d,k, ,c,l,i,e,n,t
Platform: UNKNOWN
Classifier: License :: OSI Approved :: MIT License
Classifier: Programming Language :: Python
Classifier: Intended Audience :: Developers
Classifier: Operating System :: OS Independent
